{
  "name": "Oscar Chong Documentation",
  "initialRoute": "introduction",
  "colors": {
    "light": {
      "brand": "#8c5cf4"
    },
    "dark": {
      "brand": "#a985f7"
    }
  },
  "navigation": {
    "tabs": [
      {
        "tab": "Documentation",
        "icon": "book",
        "groups": [
          {
            "group": "Getting Started",
            "icon": "rocket",
            "pages": [
              {
                "title": "Introduction",
                "path": "introduction",
                "icon": "star"
              },
              {
                "title": "Quickstart",
                "path": "quickstart",
                "icon": "zap"
              }
            ]
          },
          {
            "group": "Core Concepts",
            "icon": "lightbulb",
            "pages": [
              {
                "title": "Concepts",
                "path": "concepts",
                "icon": "file-text"
              }
            ]
          },
          {
            "group": "Guides",
            "icon": "compass",
            "pages": [
              {
                "title": "Guide",
                "path": "guide",
                "icon": "book"
              }
            ]
          }
        ]
      },
      {
        "tab": "API Reference",
        "icon": "code",
        "groups": [
          {
            "group": "Endpoints",
            "icon": "terminal",
            "openapi": "openapi.yaml"
          }
        ]
      },
      {
        "tab": "Changelog",
        "icon": "clock",
        "pages": [
          {
            "title": "Release History",
            "path": "changelog",
            "icon": "history"
          }
        ]
      }
    ]
  }
}